{
   "allLocations": {
      "chapelhill-nc": {
         "location": "Chapel Hill",
         "locationID": "0",
         "email": "chapelhill-nc@gmail.com",
         "thisYear": {
            "ggleSheetID": "1_iQHVBzAFVQbuKZKpdGbKA3szeU1WM-KL5_qHN5b46k"
         },
         "lastYear": {
            "ggleSheetID": "1O_J5NmoNfz65HqGqT7vKPDZqzbmUbMW8CbXB2pDpBcQ"
         },
         "stats": {
            "ggleSheetID": "1OGqfpQ57Z_V9E6wnOeYnQaZ14DMzHetKcPic_ZYVyeA"
         },
         "membership": {
            "ggleSheetID": "1HA1lPanT9fX5kpcpDLLkTGfbbUlmdNvymlvAZjY5Nc0"
         }
      }
   }
}